.gitignore
.pylintrc
LICENSE
README.rst
requirements.txt
setup.py
startup.py
.github/workflows/build.yml
.github/workflows/release.yml
docs/api.rst
docs/conf.py
docs/examples.rst
docs/index.rst
docs/installation.rst
docs/_static/.gitignore
examples/64x32_two_lines.py
examples/background.jpg
examples/demo.py
examples/logo.png
examples/multicolored_text.py
examples/opensign_is_available.py
examples/stroked_text.py
examples/stroked_text_on_background_with_shadow.py
examples/text_on_background.py
opensign/__init__.py
opensign/canvas.py
opensign.egg-info/PKG-INFO
opensign.egg-info/SOURCES.txt
opensign.egg-info/dependency_links.txt
opensign.egg-info/requires.txt
opensign.egg-info/top_level.txt