Metadata-Version: 2.1
Name: opensign
Version: 0.9.0
Summary: A library to facilitate easy RGB Matrix Sign Animations.
Home-page: https://github.com/makermelissa/OpenSign
Author: Melissa LeBlanc-Williams
Author-email: melissa@makermelissa.com
License: MIT
Keywords: opensign open sign rgb matrix led animation hzeller makermelissa
Platform: UNKNOWN
Classifier: Development Status :: 3 - Alpha
Classifier: Intended Audience :: Developers
Classifier: Topic :: Software Development :: Libraries
Classifier: Topic :: System :: Hardware
Classifier: License :: OSI Approved :: MIT License
Classifier: Programming Language :: Python :: 3
Classifier: Programming Language :: Python :: 3.4
Classifier: Programming Language :: Python :: 3.5
License-File: LICENSE
